ScreenRecorder.py
ScreenRecorder-1.0.6.dist-info/LICENSE
ScreenRecorder-1.0.6.dist-info/METADATA
ScreenRecorder-1.0.6.dist-info/WHEEL
ScreenRecorder-1.0.6.dist-info/top_level.txt
ScreenRecorder-1.0.6.dist-info/RECORD
