Metadata-Version: 2.1
Name: ScreenRecorder
Version: 1.0.6
Summary: A screen recorder.
Home-page: https://pypi.org/project/ScreenRecorder
Author: foo
Author-email: foo@foo.com
License: MIT
Platform: Windows
Classifier: Development Status :: 5 - Production/Stable
Classifier: Intended Audience :: Developers
Classifier: Intended Audience :: End Users/Desktop
Classifier: License :: OSI Approved :: MIT License
Classifier: Natural Language :: Chinese (Simplified)
Classifier: Programming Language :: Python :: 3
Classifier: Programming Language :: Python :: 3.6
Classifier: Programming Language :: Python :: 3.7
Classifier: Programming Language :: Python :: 3.8
Classifier: Programming Language :: Python :: 3.9
Requires-Python: >=3.6
Requires-Dist: keyboard
Requires-Dist: moviepy
Requires-Dist: pyaudio
Requires-Dist: pyautogui
Requires-Dist: pygame
